g4rzk/color.py
g4rzk/datetime.py
g4rzk/module.py
g4rzk/useragent.py
g4rzk-0.5.dist-info/LICENSE
g4rzk-0.5.dist-info/METADATA
g4rzk-0.5.dist-info/WHEEL
g4rzk-0.5.dist-info/top_level.txt
g4rzk-0.5.dist-info/RECORD
