Metadata-Version: 2.1
Name: g4rzk
Version: 0.5
Summary: Sebuah module packages yang biasa di pakai buat anu ea, ytta
Author: Angga Kurniawan
Author-email: g4rzkurniawan@gmail.com
License: MIT
Keywords: g4rzk,garzk,garz.id,anggaxd
Classifier: Development Status :: 3 - Alpha
Classifier: Intended Audience :: Developers
Classifier: Topic :: Software Development :: Build Tools
Classifier: License :: OSI Approved :: MIT License
Classifier: Programming Language :: Python :: 3.10
License-File: LICENSE
Requires-Dist: bs4
Requires-Dist: rich
Requires-Dist: inquirer
Requires-Dist: requests
